battery_analyser/__init__.py
battery_analyser/predict.py
battery_analyser-0.1.0.dist-info/METADATA
battery_analyser-0.1.0.dist-info/WHEEL
battery_analyser-0.1.0.dist-info/RECORD
